docs/Makefile
docs/source/animations.rst
docs/source/api.rst
docs/source/api_bibliography.rst
docs/source/api_presentation.rst
docs/source/api_server.rst
docs/source/api_shape.rst
docs/source/api_slide.rst
docs/source/api_utils.rst
docs/source/bokeh.rst
docs/source/citation.rst
docs/source/conf.py
docs/source/embed.rst
docs/source/favicon.ico
docs/source/hot_reload.rst
docs/source/image.rst
docs/source/import_example.py
docs/source/index.rst
docs/source/installation.rst
docs/source/markdown.rst
docs/source/matplotlib.rst
docs/source/model.rst
docs/source/molecule.rst
docs/source/notebook.rst
docs/source/plotly.rst
docs/source/python.rst
docs/source/reference.rst
docs/source/shape.rst
docs/source/started.rst
docs/source/youtube.rst
docs/source/_static/custom.css
paper/figure.pdf
paper/paper.bib
paper/paper.md
plixlab/Bibliography.py
plixlab/__init__.py
plixlab/_version.py
plixlab/presentation.py
plixlab/server.py
plixlab/shape.py
plixlab/slide.py
plixlab/utils.py
plixlab/web/index.html
plixlab/web/assets/favicon.ico
plixlab/web/assets/css/plixlab.css
plixlab/web/assets/js/load.js
plixlab/web/assets/js/load_standalone.js
plixlab/web/assets/js/plixlab.js
plixlab-0.5.10.dist-info/licenses/LICENSE
tests/conftest.py
tests/run.py
tests/assets/biblio.bib
tests/assets/image.png
tests/assets/logo.png
tests/assets/model.glb
tests/assets/mpl_style_light
tests/reference/animation.plx
tests/reference/bokeh.plx
tests/reference/citation.plx
tests/reference/demo.plx
tests/reference/embed.plx
tests/reference/equation.plx
tests/reference/image.plx
tests/reference/logo.plx
tests/reference/markdown.plx
tests/reference/matplotlib.plx
tests/reference/model.plx
tests/reference/molecule.plx
tests/reference/multislide.plx
tests/reference/plotly.plx
tests/reference/python.plx
tests/reference/shape.plx
tests/reference/welcome.plx
tests/reference/youtube.plx
plixlab-0.5.10.dist-info/METADATA
plixlab-0.5.10.dist-info/WHEEL
plixlab-0.5.10.dist-info/top_level.txt
plixlab-0.5.10.dist-info/RECORD
