Metadata-Version: 2.4
Name: plixlab
Version: 0.5.10
Summary: Interactive scientific presentations in Python
Author-email: Giuseppe Romano <romanog@mit.edu>
License-Expression: AGPL-3.0-or-later
Project-URL: Homepage, https://github.com/plixlabdev/plixlab
Project-URL: Documentation, https://plixlabdev.github.io/plixlab/
Project-URL: Repository, https://github.com/plixlabdev/plixlab
Keywords: presentations,scientific,interactive,visualization,jupyter
Classifier: Intended Audience :: Science/Research
Classifier: Intended Audience :: Education
Classifier: Programming Language :: Python :: 3.11
Classifier: Programming Language :: Python :: 3.12
Classifier: Topic :: Scientific/Engineering :: Visualization
Classifier: Topic :: Multimedia :: Graphics :: Presentation
Requires-Python: >=3.11
License-File: LICENSE
Requires-Dist: requests
Requires-Dist: plotly
Requires-Dist: matplotlib
Requires-Dist: pycairo
Requires-Dist: bibtexparser==1.4.3
Requires-Dist: hash_dict
Requires-Dist: jsonpointer
Requires-Dist: msgpack
Requires-Dist: watchdog
Requires-Dist: tornado
Requires-Dist: nest_asyncio
Requires-Dist: jsonpatch
Requires-Dist: dict_hash
Requires-Dist: pandas
Requires-Dist: bokeh
Requires-Dist: beautifulsoup4
Provides-Extra: docs
Requires-Dist: sphinx>=7; extra == "docs"
Requires-Dist: sphinx-book-theme>=1.1.4; extra == "docs"
Requires-Dist: sphinx-copybutton; extra == "docs"
Requires-Dist: sphinxcontrib-video; extra == "docs"
Requires-Dist: setuptools-scm; extra == "docs"
Requires-Dist: roman; extra == "docs"
Requires-Dist: sphinx-autodoc-typehints; extra == "docs"
Provides-Extra: dev
Requires-Dist: pytest>=6.0; extra == "dev"
Requires-Dist: pytest-cov; extra == "dev"
Dynamic: license-file
